{
    "strokes": [
        {
            "id": 0,
            "type": "line",
            "coords": [
                -0.005,
                0.005,
                0.0,
                0.005,
                0.005,
                0.0
            ]
        },
        {
            "id": 1,
            "type": "line",
            "coords": [
                -0.005,
                -0.005,
                0.0,
                -0.005,
                0.005,
                0.0
            ]
        },
        {
            "id": 2,
            "type": "line",
            "coords": [
                -0.005,
                -0.005,
                0.0,
                0.005,
                -0.005,
                0.0
            ]
        },
        {
            "id": 3,
            "type": "line",
            "coords": [
                0.005,
                -0.005,
                0.0,
                0.005,
                0.005,
                0.0
            ]
        },
        {
            "id": 4,
            "type": "line",
            "coords": [
                -0.005,
                0.005,
                0.0,
                -0.005,
                0.005,
                0.01
            ]
        },
        {
            "id": 5,
            "type": "line",
            "coords": [
                0.005,
                0.005,
                0.01,
                0.005,
                0.005,
                0.0
            ]
        },
        {
            "id": 6,
            "type": "line",
            "coords": [
                -0.005,
                0.005,
                0.01,
                0.005,
                0.005,
                0.01
            ]
        },
        {
            "id": 7,
            "type": "line",
            "coords": [
                -0.005,
                -0.005,
                0.0,
                -0.005,
                -0.005,
                0.01
            ]
        },
        {
            "id": 8,
            "type": "line",
            "coords": [
                -0.005,
                -0.005,
                0.01,
                -0.005,
                0.005,
                0.01
            ]
        },
        {
            "id": 9,
            "type": "line",
            "coords": [
                0.005,
                -0.005,
                0.01,
                0.005,
                -0.005,
                0.0
            ]
        },
        {
            "id": 10,
            "type": "line",
            "coords": [
                -0.005,
                -0.005,
                0.01,
                0.005,
                -0.005,
                0.01
            ]
        },
        {
            "id": 11,
            "type": "line",
            "coords": [
                0.005,
                -0.005,
                0.01,
                0.005,
                0.005,
                0.01
            ]
        },
        {
            "id": 12,
            "type": "line",
            "coords": [
                -0.0025,
                0.005,
                0.01,
                -0.0024999999999999996,
                -0.005,
                0.01
            ]
        },
        {
            "id": 13,
            "type": "line",
            "coords": [
                0.0025,
                -0.005,
                0.01,
                0.0024999999999999996,
                0.005,
                0.01
            ]
        },
        {
            "id": 14,
            "type": "line",
            "coords": [
                -0.005,
                0.005,
                0.0075,
                -0.005,
                -0.005,
                0.0075
            ]
        },
        {
            "id": 15,
            "type": "line",
            "coords": [
                0.0025,
                -0.005,
                0.0075,
                0.0025,
                0.005,
                0.0075
            ]
        },
        {
            "id": 16,
            "type": "line",
            "coords": [
                0.0025,
                -0.005,
                0.0025,
                0.0025,
                0.005,
                0.0025
            ]
        },
        {
            "id": 17,
            "type": "curve",
            "coords": [
                0.0,
                -0.005,
                0.0025,
                0.0,
                -0.005,
                0.0025,
                0.0002178907,
                -0.005,
                0.0025095134
            ]
        },
        {
            "id": 18,
            "type": "curve",
            "coords": [
                0.0,
                0.005,
                0.0025,
                0.0,
                0.005,
                0.0025,
                0.00021779432,
                0.005,
                0.002509505
            ]
        },
        {
            "id": 19,
            "type": "curve",
            "coords": [
                0.00220779,
                -0.005,
                0.00383207,
                0.00224145,
                0.005,
                0.00389673,
                0.00223542,
                0.00198647,
                0.00388515
            ]
        },
        {
            "id": 20,
            "type": "curve",
            "coords": [
                -0.00179499,
                -0.005,
                0.00673807,
                -0.00184401,
                0.005,
                0.00668456,
                -0.0018173,
                -0.00163845,
                0.00671372
            ]
        },
        {
            "id": 21,
            "type": "line",
            "coords": [
                0.005,
                -0.0025,
                0.0075,
                0.0,
                -0.0025,
                0.0075
            ]
        },
        {
            "id": 22,
            "type": "line",
            "coords": [
                0.0,
                0.0025,
                0.0075,
                0.005,
                0.0025,
                0.0075
            ]
        },
        {
            "id": 23,
            "type": "line",
            "coords": [
                0.005,
                -0.0025,
                0.0025,
                0.0,
                -0.0025,
                0.0025
            ]
        },
        {
            "id": 24,
            "type": "line",
            "coords": [
                0.005,
                0.0025,
                0.0025,
                0.0,
                0.0025,
                0.0025
            ]
        },
        {
            "id": 25,
            "type": "curve",
            "coords": [
                -4.5924256e-19,
                4.5924256e-19,
                0.0075,
                1.5308085e-19,
                -1.5308085e-19,
                0.0025,
                0.00030691287,
                -0.00030691287,
                0.0074810893
            ]
        },
        {
            "id": 26,
            "type": "curve",
            "coords": [
                -4.5924256e-19,
                -4.5924256e-19,
                0.0025,
                1.5308085e-19,
                1.5308085e-19,
                0.0075,
                0.00030691287,
                0.00030691287,
                0.0025189107
            ]
        },
        {
            "id": 27,
            "type": "curve",
            "coords": [
                0.005,
                0.0,
                0.0025,
                0.005,
                0.0,
                0.0025,
                0.005,
                0.0002178907,
                0.0025095134
            ]
        },
        {
            "id": 28,
            "type": "curve",
            "coords": [
                0.0022081,
                -0.005,
                0.00383267,
                0.00223465,
                -0.00223465,
                0.00388035,
                0.00223969,
                -0.00297375,
                0.00389336
            ]
        },
        {
            "id": 29,
            "type": "curve",
            "coords": [
                0.00222699,
                0.00222699,
                0.00386482,
                0.00222608,
                0.005,
                0.00386722,
                0.00222787,
                0.00281404,
                0.0038666
            ]
        },
        {
            "id": 30,
            "type": "curve",
            "coords": [
                0.005,
                -0.0018335,
                0.00330396,
                0.00189879,
                -0.00189879,
                0.00337521,
                0.00247265,
                -0.00188848,
                0.00336397
            ]
        },
        {
            "id": 31,
            "type": "curve",
            "coords": [
                0.00145469,
                0.00145469,
                0.00703196,
                0.005,
                0.00139469,
                0.00707288,
                0.00267366,
                0.00143394,
                0.00704788
            ]
        },
        {
            "id": 32,
            "type": "curve",
            "coords": [
                -0.0024900818,
                0.005,
                0.01,
                -0.005,
                0.005,
                0.0074900817,
                -0.002697349202145095,
                0.005,
                0.009991427356493663
            ]
        },
        {
            "id": 33,
            "type": "curve",
            "coords": [
                -0.0024900818,
                -0.005,
                0.01,
                -0.005,
                -0.005,
                0.0074900817,
                -0.002697349202145095,
                -0.005,
                0.009991427356493663
            ]
        },
        {
            "id": 34,
            "type": "curve",
            "coords": [
                0.005,
                0.005,
                0.0074900817,
                0.0024900818,
                0.005,
                0.01,
                0.004991427356835214,
                0.005,
                0.007697349110403029
            ]
        },
        {
            "id": 35,
            "type": "curve",
            "coords": [
                0.005,
                0.00022246836,
                0.0074900817,
                0.005,
                -0.00022246836,
                0.0074900817,
                0.004999981,
                2.5585643e-05,
                0.007499869
            ]
        },
        {
            "id": 36,
            "type": "line",
            "coords": [
                0.005,
                0.00022246836,
                0.0074900817,
                0.005,
                0.005,
                0.0074900817
            ]
        },
        {
            "id": 37,
            "type": "line",
            "coords": [
                0.005,
                -0.005,
                0.0074900817,
                0.005,
                -0.00022246836,
                0.0074900817
            ]
        },
        {
            "id": 38,
            "type": "curve",
            "coords": [
                0.0024900818,
                -0.005,
                0.01,
                0.005,
                -0.005,
                0.0074900817,
                0.002708813,
                -0.005,
                0.009990451
            ]
        },
        {
            "id": 39,
            "type": "line",
            "coords": [
                -0.005,
                0.005,
                0.0074900817,
                -0.005,
                0.005,
                0.0
            ]
        },
        {
            "id": 40,
            "type": "line",
            "coords": [
                -0.005,
                -0.005,
                0.0074900817,
                -0.005,
                -0.005,
                0.0
            ]
        },
        {
            "id": 41,
            "type": "line",
            "coords": [
                0.005,
                -0.005,
                0.0074900817,
                0.005,
                -0.005,
                0.0
            ]
        },
        {
            "id": 42,
            "type": "line",
            "coords": [
                0.005,
                0.005,
                0.0074900817,
                0.005,
                0.005,
                0.0
            ]
        },
        {
            "id": 43,
            "type": "line",
            "coords": [
                -0.0024900818,
                -0.005,
                0.01,
                0.0024900818,
                -0.005,
                0.01
            ]
        },
        {
            "id": 44,
            "type": "line",
            "coords": [
                0.0024900818,
                0.005,
                0.01,
                -0.0024900818,
                0.005,
                0.01
            ]
        },
        {
            "id": 45,
            "type": "curve",
            "coords": [
                0.005,
                -0.00022246836,
                0.0074900817,
                0.005,
                0.00022246836,
                0.0074900817,
                0.005,
                -0.00043864804,
                0.0074612168
            ]
        },
        {
            "id": 46,
            "type": "curve",
            "coords": [
                -0.00396417,
                0.005,
                0.00951965,
                -0.00390479,
                -0.005,
                0.00956197,
                -0.00392971,
                -0.000245066,
                0.00954609
            ]
        }
    ],
    "intersections": [],
    "construction_lines": []
}