{
    "strokes": [
        {
            "id": 0,
            "type": "line",
            "coords": [
                -0.005,
                0.0,
                0.005,
                0.005,
                0.0,
                0.005
            ]
        },
        {
            "id": 1,
            "type": "line",
            "coords": [
                -0.005,
                0.0,
                -0.005,
                -0.005,
                0.0,
                0.005
            ]
        },
        {
            "id": 2,
            "type": "line",
            "coords": [
                -0.005,
                0.0,
                -0.005,
                0.005,
                0.0,
                -0.005
            ]
        },
        {
            "id": 3,
            "type": "line",
            "coords": [
                0.005,
                0.0,
                -0.005,
                0.005,
                0.0,
                0.005
            ]
        },
        {
            "id": 4,
            "type": "line",
            "coords": [
                -0.005,
                0.0,
                0.005,
                -0.005,
                -0.01,
                0.005
            ]
        },
        {
            "id": 5,
            "type": "line",
            "coords": [
                0.005,
                -0.01,
                0.005,
                0.005,
                0.0,
                0.005
            ]
        },
        {
            "id": 6,
            "type": "line",
            "coords": [
                -0.005,
                -0.01,
                0.005,
                0.005,
                -0.01,
                0.005
            ]
        },
        {
            "id": 7,
            "type": "line",
            "coords": [
                -0.005,
                0.0,
                -0.005,
                -0.005,
                -0.01,
                -0.005
            ]
        },
        {
            "id": 8,
            "type": "line",
            "coords": [
                -0.005,
                -0.01,
                -0.005,
                -0.005,
                -0.01,
                0.005
            ]
        },
        {
            "id": 9,
            "type": "line",
            "coords": [
                0.005,
                -0.01,
                -0.005,
                0.005,
                0.0,
                -0.005
            ]
        },
        {
            "id": 10,
            "type": "line",
            "coords": [
                -0.005,
                -0.01,
                -0.005,
                0.005,
                -0.01,
                -0.005
            ]
        },
        {
            "id": 11,
            "type": "line",
            "coords": [
                0.005,
                -0.01,
                -0.005,
                0.005,
                -0.01,
                0.005
            ]
        },
        {
            "id": 12,
            "type": "line",
            "coords": [
                -0.005,
                -0.0075,
                0.0025,
                0.005,
                -0.0075,
                0.0025
            ]
        },
        {
            "id": 13,
            "type": "curve",
            "coords": [
                0.005,
                -0.005,
                -0.0025,
                0.005,
                -0.005,
                -0.0025,
                0.005,
                -0.0047821095,
                -0.0024904867
            ]
        },
        {
            "id": 14,
            "type": "curve",
            "coords": [
                -0.005,
                -0.005,
                -0.0025,
                -0.005,
                -0.005,
                -0.0025,
                -0.005,
                -0.0047822054,
                -0.002490495
            ]
        },
        {
            "id": 15,
            "type": "curve",
            "coords": [
                0.005,
                -0.0038068,
                0.00219463,
                -0.005,
                -0.00387138,
                0.00222825,
                0.000122833,
                -0.00384435,
                0.00221418
            ]
        },
        {
            "id": 16,
            "type": "curve",
            "coords": [
                0.005,
                -0.00662159,
                -0.00190171,
                -0.005,
                -0.00656499,
                -0.00194732,
                0.00187195,
                -0.00660697,
                -0.00191511
            ]
        },
        {
            "id": 17,
            "type": "line",
            "coords": [
                -0.00125,
                -0.01,
                0.00375,
                -0.00125,
                -0.013750000000000002,
                0.00375
            ]
        },
        {
            "id": 18,
            "type": "line",
            "coords": [
                0.00125,
                -0.013750000000000002,
                0.00375,
                0.00125,
                -0.01,
                0.00375
            ]
        },
        {
            "id": 19,
            "type": "line",
            "coords": [
                -0.00125,
                -0.01,
                0.00125,
                -0.00125,
                -0.013750000000000002,
                0.00125
            ]
        },
        {
            "id": 20,
            "type": "line",
            "coords": [
                0.00125,
                -0.01,
                0.00125,
                0.00125,
                -0.013750000000000002,
                0.00125
            ]
        },
        {
            "id": 21,
            "type": "curve",
            "coords": [
                0.0,
                -0.01,
                0.00125,
                0.0,
                -0.01,
                0.00125,
                0.00010894535,
                -0.01,
                0.0012547567
            ]
        },
        {
            "id": 22,
            "type": "curve",
            "coords": [
                0.0,
                -0.01375,
                0.00125,
                0.0,
                -0.01375,
                0.00125,
                0.00010894535,
                -0.01375,
                0.0012547567
            ]
        },
        {
            "id": 23,
            "type": "curve",
            "coords": [
                -0.005,
                -0.009051852,
                -0.005,
                -0.005,
                -0.01,
                -0.004051852,
                -0.005,
                -0.009130149441250901,
                -0.004996761593875288
            ]
        },
        {
            "id": 24,
            "type": "curve",
            "coords": [
                0.005,
                -0.009051852,
                -0.005,
                0.005,
                -0.01,
                -0.004051852,
                0.005,
                -0.009130149441250901,
                -0.004996761593875288
            ]
        },
        {
            "id": 25,
            "type": "curve",
            "coords": [
                0.005,
                -0.009051852,
                0.005,
                0.005,
                -0.01,
                0.004051852,
                0.005,
                -0.009130149441250901,
                0.004996761593875288
            ]
        },
        {
            "id": 26,
            "type": "curve",
            "coords": [
                -0.005,
                -0.009051852,
                0.005,
                -0.005,
                -0.01,
                0.004051852,
                -0.005,
                -0.009130149441250901,
                0.004996761593875288
            ]
        },
        {
            "id": 27,
            "type": "line",
            "coords": [
                -0.005,
                -0.009051852,
                -0.005,
                0.005,
                -0.009051852,
                -0.005
            ]
        },
        {
            "id": 28,
            "type": "line",
            "coords": [
                0.005,
                -0.009051852,
                0.005,
                -0.005,
                -0.009051852,
                0.005
            ]
        },
        {
            "id": 29,
            "type": "line",
            "coords": [
                0.005,
                -0.01,
                0.004051852,
                -0.005,
                -0.01,
                0.004051852
            ]
        },
        {
            "id": 30,
            "type": "line",
            "coords": [
                -0.005,
                -0.01,
                -0.004051852,
                0.005,
                -0.01,
                -0.004051852
            ]
        },
        {
            "id": 31,
            "type": "line",
            "coords": [
                -0.005,
                -0.009051852,
                0.005,
                -0.005,
                0.0,
                0.005
            ]
        },
        {
            "id": 32,
            "type": "line",
            "coords": [
                -0.005,
                -0.009051852,
                -0.005,
                -0.005,
                0.0,
                -0.005
            ]
        },
        {
            "id": 33,
            "type": "line",
            "coords": [
                0.005,
                -0.009051852,
                -0.005,
                0.005,
                0.0,
                -0.005
            ]
        },
        {
            "id": 34,
            "type": "line",
            "coords": [
                0.005,
                -0.009051852,
                0.005,
                0.005,
                0.0,
                0.005
            ]
        },
        {
            "id": 35,
            "type": "line",
            "coords": [
                0.005,
                -0.01,
                -0.004051852,
                0.005,
                -0.01,
                0.004051852
            ]
        },
        {
            "id": 36,
            "type": "line",
            "coords": [
                -0.005,
                -0.01,
                0.004051852,
                -0.005,
                -0.01,
                -0.004051852
            ]
        }
    ],
    "intersections": [],
    "construction_lines": []
}